{
  "schema_version": 1,
  "source": "VIDA (Kaggle: benjameeper/movie-violencesexprofanity-data)",
  "imdb_id": "tt3111426",
  "title": "Lost Girls",
  "scenes": [
    {
      "start_ms": 96000,
      "end_ms": 108000,
      "action": "Remove",
      "category": "immodesty",
      "note": "This data was obtained from https://www.kaggle.com/datasets/benjameeper/movie-violencesexprofanity-data. Timestamps may be incorrect. Please adjust the timing offsets as necessary.",
      "enabled": true
    },
    {
      "start_ms": 114000,
      "end_ms": 120000,
      "action": "Remove",
      "category": "sexual_reference",
      "note": "",
      "enabled": true
    },
    {
      "start_ms": 120000,
      "end_ms": 121000,
      "action": "Remove",
      "category": "immodesty",
      "note": "",
      "enabled": true
    },
    {
      "start_ms": 522000,
      "end_ms": 523000,
      "action": "Remove",
      "category": "non_graphic",
      "note": "",
      "enabled": true
    },
    {
      "start_ms": 1182000,
      "end_ms": 1183000,
      "action": "Remove",
      "category": "sexual_reference",
      "note": "",
      "enabled": true
    },
    {
      "start_ms": 1440000,
      "end_ms": 1441000,
      "action": "Remove",
      "category": "sexual_reference",
      "note": "",
      "enabled": true
    },
    {
      "start_ms": 1446000,
      "end_ms": 1447000,
      "action": "Remove",
      "category": "sexual_reference",
      "note": "",
      "enabled": true
    },
    {
      "start_ms": 1464000,
      "end_ms": 1470000,
      "action": "Remove",
      "category": "sexual_reference",
      "note": "",
      "enabled": true
    },
    {
      "start_ms": 1494000,
      "end_ms": 1495000,
      "action": "Remove",
      "category": "sexual_reference",
      "note": "",
      "enabled": true
    },
    {
      "start_ms": 1530000,
      "end_ms": 1531000,
      "action": "Remove",
      "category": "sexual_reference",
      "note": "",
      "enabled": true
    },
    {
      "start_ms": 1536000,
      "end_ms": 1537000,
      "action": "Remove",
      "category": "sexual_reference",
      "note": "",
      "enabled": true
    },
    {
      "start_ms": 1566000,
      "end_ms": 1567000,
      "action": "Remove",
      "category": "sexual_reference",
      "note": "",
      "enabled": true
    },
    {
      "start_ms": 1632000,
      "end_ms": 1633000,
      "action": "Remove",
      "category": "sexual_reference",
      "note": "",
      "enabled": true
    },
    {
      "start_ms": 1644000,
      "end_ms": 1645000,
      "action": "Remove",
      "category": "sexual_reference",
      "note": "",
      "enabled": true
    },
    {
      "start_ms": 1740000,
      "end_ms": 1741000,
      "action": "Remove",
      "category": "sexual_reference",
      "note": "",
      "enabled": true
    },
    {
      "start_ms": 1902000,
      "end_ms": 1920000,
      "action": "Remove",
      "category": "immodesty",
      "note": "",
      "enabled": true
    },
    {
      "start_ms": 1956000,
      "end_ms": 1962000,
      "action": "Remove",
      "category": "immodesty",
      "note": "",
      "enabled": true
    },
    {
      "start_ms": 1968000,
      "end_ms": 1974000,
      "action": "Remove",
      "category": "immodesty",
      "note": "",
      "enabled": true
    },
    {
      "start_ms": 1974000,
      "end_ms": 1980000,
      "action": "Remove",
      "category": "immodesty",
      "note": "",
      "enabled": true
    },
    {
      "start_ms": 1986000,
      "end_ms": 1992000,
      "action": "Remove",
      "category": "immodesty",
      "note": "",
      "enabled": true
    },
    {
      "start_ms": 1998000,
      "end_ms": 1999000,
      "action": "Remove",
      "category": "immodesty",
      "note": "",
      "enabled": true
    },
    {
      "start_ms": 2052000,
      "end_ms": 2058000,
      "action": "Remove",
      "category": "immodesty",
      "note": "",
      "enabled": true
    },
    {
      "start_ms": 2052000,
      "end_ms": 2058000,
      "action": "Remove",
      "category": "sexual_reference",
      "note": "",
      "enabled": true
    },
    {
      "start_ms": 2082000,
      "end_ms": 2088000,
      "action": "Remove",
      "category": "immodesty",
      "note": "",
      "enabled": true
    },
    {
      "start_ms": 2268000,
      "end_ms": 2269000,
      "action": "Remove",
      "category": "racial_slurs",
      "note": "",
      "enabled": true
    },
    {
      "start_ms": 2598000,
      "end_ms": 2599000,
      "action": "Remove",
      "category": "sexual_reference",
      "note": "",
      "enabled": true
    },
    {
      "start_ms": 2634000,
      "end_ms": 2635000,
      "action": "Remove",
      "category": "sexual_reference",
      "note": "",
      "enabled": true
    },
    {
      "start_ms": 2838000,
      "end_ms": 2839000,
      "action": "Remove",
      "category": "sexual_reference",
      "note": "",
      "enabled": true
    },
    {
      "start_ms": 3312000,
      "end_ms": 3313000,
      "action": "Remove",
      "category": "immodesty",
      "note": "",
      "enabled": true
    },
    {
      "start_ms": 3606000,
      "end_ms": 3612000,
      "action": "Remove",
      "category": "sexual_reference",
      "note": "",
      "enabled": true
    },
    {
      "start_ms": 4206000,
      "end_ms": 4207000,
      "action": "Remove",
      "category": "immodesty",
      "note": "",
      "enabled": true
    },
    {
      "start_ms": 4668000,
      "end_ms": 4680000,
      "action": "Remove",
      "category": "immodesty",
      "note": "",
      "enabled": true
    },
    {
      "start_ms": 4668000,
      "end_ms": 4680000,
      "action": "Remove",
      "category": "sexually_suggestive",
      "note": "",
      "enabled": true
    },
    {
      "start_ms": 4686000,
      "end_ms": 4687000,
      "action": "Remove",
      "category": "immodesty",
      "note": "",
      "enabled": true
    },
    {
      "start_ms": 4686000,
      "end_ms": 4687000,
      "action": "Remove",
      "category": "sexually_suggestive",
      "note": "",
      "enabled": true
    },
    {
      "start_ms": 4734000,
      "end_ms": 4735000,
      "action": "Remove",
      "category": "sexual_reference",
      "note": "",
      "enabled": true
    },
    {
      "start_ms": 4764000,
      "end_ms": 4765000,
      "action": "Remove",
      "category": "sexual_reference",
      "note": "",
      "enabled": true
    },
    {
      "start_ms": 5058000,
      "end_ms": 5059000,
      "action": "Remove",
      "category": "graphic",
      "note": "",
      "enabled": true
    },
    {
      "start_ms": 5082000,
      "end_ms": 5112000,
      "action": "Remove",
      "category": "disturbing_images",
      "note": "",
      "enabled": true
    },
    {
      "start_ms": 5376000,
      "end_ms": 5382000,
      "action": "Remove",
      "category": "non_graphic",
      "note": "",
      "enabled": true
    },
    {
      "start_ms": 5394000,
      "end_ms": 5395000,
      "action": "Remove",
      "category": "non_graphic",
      "note": "",
      "enabled": true
    },
    {
      "start_ms": 5418000,
      "end_ms": 5424000,
      "action": "Remove",
      "category": "non_graphic",
      "note": "",
      "enabled": true
    }
  ]
}
