{
  "schema_version": 1,
  "source": "VIDA (Kaggle: benjameeper/movie-violencesexprofanity-data)",
  "imdb_id": "tt0864835",
  "title": "Mr. Peabody & Sherman",
  "scenes": [
    {
      "start_ms": 138000,
      "end_ms": 139000,
      "action": "Remove",
      "category": "bodily_functions",
      "note": "This data was obtained from https://www.kaggle.com/datasets/benjameeper/movie-violencesexprofanity-data. Timestamps may be incorrect. Please adjust the timing offsets as necessary.",
      "enabled": true
    },
    {
      "start_ms": 300000,
      "end_ms": 306000,
      "action": "Remove",
      "category": "non_graphic",
      "note": "",
      "enabled": true
    },
    {
      "start_ms": 366000,
      "end_ms": 367000,
      "action": "Remove",
      "category": "non_graphic",
      "note": "",
      "enabled": true
    },
    {
      "start_ms": 384000,
      "end_ms": 414000,
      "action": "Remove",
      "category": "violence_implied",
      "note": "",
      "enabled": true
    },
    {
      "start_ms": 498000,
      "end_ms": 499000,
      "action": "Remove",
      "category": "non_graphic",
      "note": "",
      "enabled": true
    },
    {
      "start_ms": 522000,
      "end_ms": 523000,
      "action": "Remove",
      "category": "immodesty",
      "note": "",
      "enabled": true
    },
    {
      "start_ms": 522000,
      "end_ms": 523000,
      "action": "Remove",
      "category": "non_graphic",
      "note": "",
      "enabled": true
    },
    {
      "start_ms": 534000,
      "end_ms": 535000,
      "action": "Remove",
      "category": "non_graphic",
      "note": "",
      "enabled": true
    },
    {
      "start_ms": 546000,
      "end_ms": 547000,
      "action": "Remove",
      "category": "non_graphic",
      "note": "",
      "enabled": true
    },
    {
      "start_ms": 576000,
      "end_ms": 588000,
      "action": "Remove",
      "category": "non_graphic",
      "note": "",
      "enabled": true
    },
    {
      "start_ms": 846000,
      "end_ms": 852000,
      "action": "Remove",
      "category": "childish_language",
      "note": "",
      "enabled": true
    },
    {
      "start_ms": 852000,
      "end_ms": 858000,
      "action": "Remove",
      "category": "childish_language",
      "note": "",
      "enabled": true
    },
    {
      "start_ms": 858000,
      "end_ms": 859000,
      "action": "Remove",
      "category": "non_graphic",
      "note": "",
      "enabled": true
    },
    {
      "start_ms": 858000,
      "end_ms": 864000,
      "action": "Remove",
      "category": "childish_language",
      "note": "",
      "enabled": true
    },
    {
      "start_ms": 870000,
      "end_ms": 876000,
      "action": "Remove",
      "category": "childish_language",
      "note": "",
      "enabled": true
    },
    {
      "start_ms": 900000,
      "end_ms": 901000,
      "action": "Remove",
      "category": "childish_language",
      "note": "",
      "enabled": true
    },
    {
      "start_ms": 900000,
      "end_ms": 918000,
      "action": "Remove",
      "category": "non_graphic",
      "note": "",
      "enabled": true
    },
    {
      "start_ms": 966000,
      "end_ms": 972000,
      "action": "Remove",
      "category": "disturbing_images",
      "note": "",
      "enabled": true
    },
    {
      "start_ms": 1200000,
      "end_ms": 1201000,
      "action": "Remove",
      "category": "nudity_without_sex",
      "note": "",
      "enabled": true
    },
    {
      "start_ms": 1470000,
      "end_ms": 1476000,
      "action": "Remove",
      "category": "childish_language",
      "note": "",
      "enabled": true
    },
    {
      "start_ms": 1554000,
      "end_ms": 1560000,
      "action": "Remove",
      "category": "non_graphic",
      "note": "",
      "enabled": true
    },
    {
      "start_ms": 1566000,
      "end_ms": 1578000,
      "action": "Remove",
      "category": "objectionable",
      "note": "",
      "enabled": true
    },
    {
      "start_ms": 1626000,
      "end_ms": 1632000,
      "action": "Remove",
      "category": "non_graphic",
      "note": "",
      "enabled": true
    },
    {
      "start_ms": 1638000,
      "end_ms": 1639000,
      "action": "Remove",
      "category": "childish_language",
      "note": "",
      "enabled": true
    },
    {
      "start_ms": 1722000,
      "end_ms": 1758000,
      "action": "Remove",
      "category": "drugs_implied",
      "note": "",
      "enabled": true
    },
    {
      "start_ms": 1758000,
      "end_ms": 1759000,
      "action": "Remove",
      "category": "drugs_legal",
      "note": "",
      "enabled": true
    },
    {
      "start_ms": 1764000,
      "end_ms": 1770000,
      "action": "Remove",
      "category": "drugs_legal",
      "note": "",
      "enabled": true
    },
    {
      "start_ms": 1806000,
      "end_ms": 1812000,
      "action": "Remove",
      "category": "childish_language",
      "note": "",
      "enabled": true
    },
    {
      "start_ms": 1824000,
      "end_ms": 1825000,
      "action": "Remove",
      "category": "childish_language",
      "note": "",
      "enabled": true
    },
    {
      "start_ms": 1878000,
      "end_ms": 1879000,
      "action": "Remove",
      "category": "bodily_functions",
      "note": "",
      "enabled": true
    },
    {
      "start_ms": 1926000,
      "end_ms": 1932000,
      "action": "Remove",
      "category": "childish_language",
      "note": "",
      "enabled": true
    },
    {
      "start_ms": 1932000,
      "end_ms": 1933000,
      "action": "Remove",
      "category": "childish_language",
      "note": "",
      "enabled": true
    },
    {
      "start_ms": 1950000,
      "end_ms": 1956000,
      "action": "Remove",
      "category": "violence_implied",
      "note": "",
      "enabled": true
    },
    {
      "start_ms": 1968000,
      "end_ms": 1969000,
      "action": "Remove",
      "category": "childish_language",
      "note": "",
      "enabled": true
    },
    {
      "start_ms": 2004000,
      "end_ms": 2005000,
      "action": "Remove",
      "category": "gore",
      "note": "",
      "enabled": true
    },
    {
      "start_ms": 2016000,
      "end_ms": 2022000,
      "action": "Remove",
      "category": "violence_implied",
      "note": "",
      "enabled": true
    },
    {
      "start_ms": 2058000,
      "end_ms": 2076000,
      "action": "Remove",
      "category": "gore",
      "note": "",
      "enabled": true
    },
    {
      "start_ms": 2148000,
      "end_ms": 2149000,
      "action": "Remove",
      "category": "childish_language",
      "note": "",
      "enabled": true
    },
    {
      "start_ms": 2256000,
      "end_ms": 2262000,
      "action": "Remove",
      "category": "non_graphic",
      "note": "",
      "enabled": true
    },
    {
      "start_ms": 2358000,
      "end_ms": 2364000,
      "action": "Remove",
      "category": "drugs_legal",
      "note": "",
      "enabled": true
    },
    {
      "start_ms": 2388000,
      "end_ms": 2389000,
      "action": "Remove",
      "category": "non_graphic",
      "note": "",
      "enabled": true
    },
    {
      "start_ms": 2394000,
      "end_ms": 2395000,
      "action": "Remove",
      "category": "non_graphic",
      "note": "",
      "enabled": true
    },
    {
      "start_ms": 2412000,
      "end_ms": 2418000,
      "action": "Remove",
      "category": "non_graphic",
      "note": "",
      "enabled": true
    },
    {
      "start_ms": 2430000,
      "end_ms": 2436000,
      "action": "Remove",
      "category": "childish_language",
      "note": "",
      "enabled": true
    },
    {
      "start_ms": 2436000,
      "end_ms": 2442000,
      "action": "Remove",
      "category": "non_graphic",
      "note": "",
      "enabled": true
    },
    {
      "start_ms": 2658000,
      "end_ms": 2664000,
      "action": "Remove",
      "category": "immodesty",
      "note": "",
      "enabled": true
    },
    {
      "start_ms": 2670000,
      "end_ms": 2671000,
      "action": "Remove",
      "category": "immodesty",
      "note": "",
      "enabled": true
    },
    {
      "start_ms": 2676000,
      "end_ms": 2677000,
      "action": "Remove",
      "category": "immodesty",
      "note": "",
      "enabled": true
    },
    {
      "start_ms": 2718000,
      "end_ms": 2724000,
      "action": "Remove",
      "category": "non_graphic",
      "note": "",
      "enabled": true
    },
    {
      "start_ms": 2724000,
      "end_ms": 2730000,
      "action": "Remove",
      "category": "non_graphic",
      "note": "",
      "enabled": true
    },
    {
      "start_ms": 2742000,
      "end_ms": 2743000,
      "action": "Remove",
      "category": "non_graphic",
      "note": "",
      "enabled": true
    },
    {
      "start_ms": 3042000,
      "end_ms": 3048000,
      "action": "Remove",
      "category": "non_graphic",
      "note": "",
      "enabled": true
    },
    {
      "start_ms": 3150000,
      "end_ms": 3156000,
      "action": "Remove",
      "category": "childish_language",
      "note": "",
      "enabled": true
    },
    {
      "start_ms": 3378000,
      "end_ms": 3379000,
      "action": "Remove",
      "category": "childish_language",
      "note": "",
      "enabled": true
    },
    {
      "start_ms": 3474000,
      "end_ms": 3486000,
      "action": "Remove",
      "category": "violence_implied",
      "note": "",
      "enabled": true
    },
    {
      "start_ms": 3516000,
      "end_ms": 3522000,
      "action": "Remove",
      "category": "childish_language",
      "note": "",
      "enabled": true
    },
    {
      "start_ms": 3522000,
      "end_ms": 3528000,
      "action": "Remove",
      "category": "childish_language",
      "note": "",
      "enabled": true
    },
    {
      "start_ms": 3528000,
      "end_ms": 3534000,
      "action": "Remove",
      "category": "non_graphic",
      "note": "",
      "enabled": true
    },
    {
      "start_ms": 3552000,
      "end_ms": 3558000,
      "action": "Remove",
      "category": "non_graphic",
      "note": "",
      "enabled": true
    },
    {
      "start_ms": 3564000,
      "end_ms": 3565000,
      "action": "Remove",
      "category": "non_graphic",
      "note": "",
      "enabled": true
    },
    {
      "start_ms": 3570000,
      "end_ms": 3571000,
      "action": "Remove",
      "category": "non_graphic",
      "note": "",
      "enabled": true
    },
    {
      "start_ms": 3684000,
      "end_ms": 3685000,
      "action": "Remove",
      "category": "non_graphic",
      "note": "",
      "enabled": true
    },
    {
      "start_ms": 3780000,
      "end_ms": 3798000,
      "action": "Remove",
      "category": "drugs_implied",
      "note": "",
      "enabled": true
    },
    {
      "start_ms": 3798000,
      "end_ms": 3799000,
      "action": "Remove",
      "category": "drugs_legal",
      "note": "",
      "enabled": true
    },
    {
      "start_ms": 4074000,
      "end_ms": 4080000,
      "action": "Remove",
      "category": "non_graphic",
      "note": "",
      "enabled": true
    },
    {
      "start_ms": 4080000,
      "end_ms": 4086000,
      "action": "Remove",
      "category": "disturbing_images",
      "note": "",
      "enabled": true
    },
    {
      "start_ms": 4152000,
      "end_ms": 4153000,
      "action": "Remove",
      "category": "non_graphic",
      "note": "",
      "enabled": true
    },
    {
      "start_ms": 4158000,
      "end_ms": 4164000,
      "action": "Remove",
      "category": "non_graphic",
      "note": "",
      "enabled": true
    },
    {
      "start_ms": 4164000,
      "end_ms": 4170000,
      "action": "Remove",
      "category": "non_graphic",
      "note": "",
      "enabled": true
    },
    {
      "start_ms": 4170000,
      "end_ms": 4171000,
      "action": "Remove",
      "category": "non_graphic",
      "note": "",
      "enabled": true
    },
    {
      "start_ms": 4200000,
      "end_ms": 4206000,
      "action": "Remove",
      "category": "non_graphic",
      "note": "",
      "enabled": true
    },
    {
      "start_ms": 4260000,
      "end_ms": 4266000,
      "action": "Remove",
      "category": "immodesty",
      "note": "",
      "enabled": true
    },
    {
      "start_ms": 4278000,
      "end_ms": 4284000,
      "action": "Remove",
      "category": "non_graphic",
      "note": "",
      "enabled": true
    },
    {
      "start_ms": 4302000,
      "end_ms": 4303000,
      "action": "Remove",
      "category": "non_graphic",
      "note": "",
      "enabled": true
    },
    {
      "start_ms": 4338000,
      "end_ms": 4339000,
      "action": "Remove",
      "category": "non_graphic",
      "note": "",
      "enabled": true
    },
    {
      "start_ms": 4350000,
      "end_ms": 4356000,
      "action": "Remove",
      "category": "non_graphic",
      "note": "",
      "enabled": true
    },
    {
      "start_ms": 4506000,
      "end_ms": 4512000,
      "action": "Remove",
      "category": "non_graphic",
      "note": "",
      "enabled": true
    },
    {
      "start_ms": 4932000,
      "end_ms": 4933000,
      "action": "Remove",
      "category": "non_graphic",
      "note": "",
      "enabled": true
    },
    {
      "start_ms": 4944000,
      "end_ms": 4950000,
      "action": "Remove",
      "category": "kissing_passion",
      "note": "",
      "enabled": true
    }
  ]
}
