{
  "schema_version": 1,
  "source": "VIDA (Kaggle: benjameeper/movie-violencesexprofanity-data)",
  "imdb_id": "tt2250912",
  "title": "Spider-Man: Homecoming: Theatrical Version",
  "scenes": [
    {
      "start_ms": 180000,
      "end_ms": 186000,
      "action": "Remove",
      "category": "non_graphic",
      "note": "This data was obtained from https://www.kaggle.com/datasets/benjameeper/movie-violencesexprofanity-data. Timestamps may be incorrect. Please adjust the timing offsets as necessary.",
      "enabled": true
    },
    {
      "start_ms": 486000,
      "end_ms": 487000,
      "action": "Remove",
      "category": "sexual_reference",
      "note": "",
      "enabled": true
    },
    {
      "start_ms": 642000,
      "end_ms": 643000,
      "action": "Remove",
      "category": "childish_language",
      "note": "",
      "enabled": true
    },
    {
      "start_ms": 666000,
      "end_ms": 667000,
      "action": "Remove",
      "category": "non_graphic",
      "note": "",
      "enabled": true
    },
    {
      "start_ms": 786000,
      "end_ms": 787000,
      "action": "Remove",
      "category": "sexually_suggestive",
      "note": "",
      "enabled": true
    },
    {
      "start_ms": 792000,
      "end_ms": 793000,
      "action": "Remove",
      "category": "sexual_reference",
      "note": "",
      "enabled": true
    },
    {
      "start_ms": 792000,
      "end_ms": 798000,
      "action": "Remove",
      "category": "sexually_suggestive",
      "note": "",
      "enabled": true
    },
    {
      "start_ms": 894000,
      "end_ms": 895000,
      "action": "Remove",
      "category": "sexual_reference",
      "note": "",
      "enabled": true
    },
    {
      "start_ms": 894000,
      "end_ms": 895000,
      "action": "Remove",
      "category": "sexual_reference",
      "note": "",
      "enabled": true
    },
    {
      "start_ms": 1002000,
      "end_ms": 1003000,
      "action": "Remove",
      "category": "non_graphic",
      "note": "",
      "enabled": true
    },
    {
      "start_ms": 1056000,
      "end_ms": 1057000,
      "action": "Remove",
      "category": "non_graphic",
      "note": "",
      "enabled": true
    },
    {
      "start_ms": 1080000,
      "end_ms": 1086000,
      "action": "Remove",
      "category": "non_graphic",
      "note": "",
      "enabled": true
    },
    {
      "start_ms": 1176000,
      "end_ms": 1182000,
      "action": "Remove",
      "category": "non_graphic",
      "note": "",
      "enabled": true
    },
    {
      "start_ms": 1182000,
      "end_ms": 1188000,
      "action": "Remove",
      "category": "non_graphic",
      "note": "",
      "enabled": true
    },
    {
      "start_ms": 1188000,
      "end_ms": 1194000,
      "action": "Remove",
      "category": "non_graphic",
      "note": "",
      "enabled": true
    },
    {
      "start_ms": 1200000,
      "end_ms": 1201000,
      "action": "Remove",
      "category": "non_graphic",
      "note": "",
      "enabled": true
    },
    {
      "start_ms": 1200000,
      "end_ms": 1206000,
      "action": "Remove",
      "category": "non_graphic",
      "note": "",
      "enabled": true
    },
    {
      "start_ms": 1212000,
      "end_ms": 1213000,
      "action": "Remove",
      "category": "non_graphic",
      "note": "",
      "enabled": true
    },
    {
      "start_ms": 1506000,
      "end_ms": 1507000,
      "action": "Remove",
      "category": "non_graphic",
      "note": "",
      "enabled": true
    },
    {
      "start_ms": 1536000,
      "end_ms": 1537000,
      "action": "Remove",
      "category": "sexually_suggestive",
      "note": "",
      "enabled": true
    },
    {
      "start_ms": 1656000,
      "end_ms": 1657000,
      "action": "Remove",
      "category": "sexual_reference",
      "note": "",
      "enabled": true
    },
    {
      "start_ms": 1668000,
      "end_ms": 1674000,
      "action": "Remove",
      "category": "immodesty",
      "note": "",
      "enabled": true
    },
    {
      "start_ms": 1710000,
      "end_ms": 1722000,
      "action": "Remove",
      "category": "immodesty",
      "note": "",
      "enabled": true
    },
    {
      "start_ms": 1872000,
      "end_ms": 1873000,
      "action": "Remove",
      "category": "childish_language",
      "note": "",
      "enabled": true
    },
    {
      "start_ms": 2004000,
      "end_ms": 2010000,
      "action": "Remove",
      "category": "non_graphic",
      "note": "",
      "enabled": true
    },
    {
      "start_ms": 2016000,
      "end_ms": 2017000,
      "action": "Remove",
      "category": "non_graphic",
      "note": "",
      "enabled": true
    },
    {
      "start_ms": 2022000,
      "end_ms": 2028000,
      "action": "Remove",
      "category": "non_graphic",
      "note": "",
      "enabled": true
    },
    {
      "start_ms": 2028000,
      "end_ms": 2034000,
      "action": "Remove",
      "category": "non_graphic",
      "note": "",
      "enabled": true
    },
    {
      "start_ms": 2052000,
      "end_ms": 2058000,
      "action": "Remove",
      "category": "non_graphic",
      "note": "",
      "enabled": true
    },
    {
      "start_ms": 2064000,
      "end_ms": 2070000,
      "action": "Remove",
      "category": "non_graphic",
      "note": "",
      "enabled": true
    },
    {
      "start_ms": 2112000,
      "end_ms": 2113000,
      "action": "Remove",
      "category": "immodesty",
      "note": "",
      "enabled": true
    },
    {
      "start_ms": 2112000,
      "end_ms": 2113000,
      "action": "Remove",
      "category": "non_graphic",
      "note": "",
      "enabled": true
    },
    {
      "start_ms": 2148000,
      "end_ms": 2190000,
      "action": "Remove",
      "category": "non_graphic",
      "note": "",
      "enabled": true
    },
    {
      "start_ms": 2274000,
      "end_ms": 2275000,
      "action": "Remove",
      "category": "drugs_legal",
      "note": "",
      "enabled": true
    },
    {
      "start_ms": 2334000,
      "end_ms": 2335000,
      "action": "Remove",
      "category": "childish_language",
      "note": "",
      "enabled": true
    },
    {
      "start_ms": 2340000,
      "end_ms": 2341000,
      "action": "Remove",
      "category": "childish_language",
      "note": "",
      "enabled": true
    },
    {
      "start_ms": 2508000,
      "end_ms": 2514000,
      "action": "Remove",
      "category": "graphic",
      "note": "",
      "enabled": true
    },
    {
      "start_ms": 2964000,
      "end_ms": 2970000,
      "action": "Remove",
      "category": "immodesty",
      "note": "",
      "enabled": true
    },
    {
      "start_ms": 2970000,
      "end_ms": 2976000,
      "action": "Remove",
      "category": "immodesty",
      "note": "",
      "enabled": true
    },
    {
      "start_ms": 3006000,
      "end_ms": 3024000,
      "action": "Remove",
      "category": "immodesty",
      "note": "",
      "enabled": true
    },
    {
      "start_ms": 3126000,
      "end_ms": 3127000,
      "action": "Remove",
      "category": "non_graphic",
      "note": "",
      "enabled": true
    },
    {
      "start_ms": 3270000,
      "end_ms": 3276000,
      "action": "Remove",
      "category": "non_graphic",
      "note": "",
      "enabled": true
    },
    {
      "start_ms": 3816000,
      "end_ms": 3822000,
      "action": "Remove",
      "category": "non_graphic",
      "note": "",
      "enabled": true
    },
    {
      "start_ms": 3834000,
      "end_ms": 3835000,
      "action": "Remove",
      "category": "non_graphic",
      "note": "",
      "enabled": true
    },
    {
      "start_ms": 3870000,
      "end_ms": 3888000,
      "action": "Remove",
      "category": "non_graphic",
      "note": "",
      "enabled": true
    },
    {
      "start_ms": 3906000,
      "end_ms": 3907000,
      "action": "Remove",
      "category": "non_graphic",
      "note": "",
      "enabled": true
    },
    {
      "start_ms": 3978000,
      "end_ms": 3979000,
      "action": "Remove",
      "category": "immodesty",
      "note": "",
      "enabled": true
    },
    {
      "start_ms": 4104000,
      "end_ms": 4110000,
      "action": "Remove",
      "category": "life_events",
      "note": "",
      "enabled": true
    },
    {
      "start_ms": 4266000,
      "end_ms": 4267000,
      "action": "Remove",
      "category": "sexual_reference",
      "note": "",
      "enabled": true
    },
    {
      "start_ms": 4464000,
      "end_ms": 4465000,
      "action": "Remove",
      "category": "non_graphic",
      "note": "",
      "enabled": true
    },
    {
      "start_ms": 4476000,
      "end_ms": 4477000,
      "action": "Remove",
      "category": "non_graphic",
      "note": "",
      "enabled": true
    },
    {
      "start_ms": 4488000,
      "end_ms": 4494000,
      "action": "Remove",
      "category": "non_graphic",
      "note": "",
      "enabled": true
    },
    {
      "start_ms": 4524000,
      "end_ms": 4525000,
      "action": "Remove",
      "category": "non_graphic",
      "note": "",
      "enabled": true
    },
    {
      "start_ms": 4572000,
      "end_ms": 4573000,
      "action": "Remove",
      "category": "non_graphic",
      "note": "",
      "enabled": true
    },
    {
      "start_ms": 5664000,
      "end_ms": 5665000,
      "action": "Remove",
      "category": "vulgar_gestures",
      "note": "",
      "enabled": true
    },
    {
      "start_ms": 5724000,
      "end_ms": 5730000,
      "action": "Remove",
      "category": "non_graphic",
      "note": "",
      "enabled": true
    },
    {
      "start_ms": 5742000,
      "end_ms": 5748000,
      "action": "Remove",
      "category": "non_graphic",
      "note": "",
      "enabled": true
    },
    {
      "start_ms": 5754000,
      "end_ms": 5755000,
      "action": "Remove",
      "category": "non_graphic",
      "note": "",
      "enabled": true
    },
    {
      "start_ms": 5934000,
      "end_ms": 5935000,
      "action": "Remove",
      "category": "non_graphic",
      "note": "",
      "enabled": true
    },
    {
      "start_ms": 5958000,
      "end_ms": 5959000,
      "action": "Remove",
      "category": "sexual_reference",
      "note": "",
      "enabled": true
    },
    {
      "start_ms": 6114000,
      "end_ms": 6115000,
      "action": "Remove",
      "category": "non_graphic",
      "note": "",
      "enabled": true
    },
    {
      "start_ms": 6372000,
      "end_ms": 6378000,
      "action": "Remove",
      "category": "non_graphic",
      "note": "",
      "enabled": true
    },
    {
      "start_ms": 6534000,
      "end_ms": 6546000,
      "action": "Remove",
      "category": "non_graphic",
      "note": "",
      "enabled": true
    },
    {
      "start_ms": 6588000,
      "end_ms": 6594000,
      "action": "Remove",
      "category": "non_graphic",
      "note": "",
      "enabled": true
    },
    {
      "start_ms": 6606000,
      "end_ms": 6618000,
      "action": "Remove",
      "category": "non_graphic",
      "note": "",
      "enabled": true
    },
    {
      "start_ms": 6660000,
      "end_ms": 6661000,
      "action": "Remove",
      "category": "non_graphic",
      "note": "",
      "enabled": true
    },
    {
      "start_ms": 6684000,
      "end_ms": 6708000,
      "action": "Remove",
      "category": "non_graphic",
      "note": "",
      "enabled": true
    },
    {
      "start_ms": 6762000,
      "end_ms": 6768000,
      "action": "Remove",
      "category": "non_graphic",
      "note": "",
      "enabled": true
    },
    {
      "start_ms": 6780000,
      "end_ms": 6786000,
      "action": "Remove",
      "category": "non_graphic",
      "note": "",
      "enabled": true
    },
    {
      "start_ms": 7314000,
      "end_ms": 7320000,
      "action": "Remove",
      "category": "kissing_normal",
      "note": "",
      "enabled": true
    }
  ]
}
