{
  "schema_version": 1,
  "source": "VIDA (Kaggle: benjameeper/movie-violencesexprofanity-data)",
  "imdb_id": "tt0787524",
  "title": "The Man Who Knew Infinity",
  "scenes": [
    {
      "start_ms": 894000,
      "end_ms": 895000,
      "action": "Remove",
      "category": "racial_slurs",
      "note": "This data was obtained from https://www.kaggle.com/datasets/benjameeper/movie-violencesexprofanity-data. Timestamps may be incorrect. Please adjust the timing offsets as necessary.",
      "enabled": true
    },
    {
      "start_ms": 894000,
      "end_ms": 900000,
      "action": "Remove",
      "category": "drugs_legal",
      "note": "",
      "enabled": true
    },
    {
      "start_ms": 1026000,
      "end_ms": 1027000,
      "action": "Remove",
      "category": "drugs_legal",
      "note": "",
      "enabled": true
    },
    {
      "start_ms": 1044000,
      "end_ms": 1050000,
      "action": "Remove",
      "category": "drugs_legal",
      "note": "",
      "enabled": true
    },
    {
      "start_ms": 1050000,
      "end_ms": 1056000,
      "action": "Remove",
      "category": "drugs_legal",
      "note": "",
      "enabled": true
    },
    {
      "start_ms": 1056000,
      "end_ms": 1062000,
      "action": "Remove",
      "category": "drugs_legal",
      "note": "",
      "enabled": true
    },
    {
      "start_ms": 1074000,
      "end_ms": 1075000,
      "action": "Remove",
      "category": "drugs_legal",
      "note": "",
      "enabled": true
    },
    {
      "start_ms": 1080000,
      "end_ms": 1086000,
      "action": "Remove",
      "category": "drugs_legal",
      "note": "",
      "enabled": true
    },
    {
      "start_ms": 1086000,
      "end_ms": 1098000,
      "action": "Remove",
      "category": "drugs_legal",
      "note": "",
      "enabled": true
    },
    {
      "start_ms": 1098000,
      "end_ms": 1104000,
      "action": "Remove",
      "category": "drugs_legal",
      "note": "",
      "enabled": true
    },
    {
      "start_ms": 1116000,
      "end_ms": 1117000,
      "action": "Remove",
      "category": "drugs_legal",
      "note": "",
      "enabled": true
    },
    {
      "start_ms": 1122000,
      "end_ms": 1123000,
      "action": "Remove",
      "category": "drugs_legal",
      "note": "",
      "enabled": true
    },
    {
      "start_ms": 1422000,
      "end_ms": 1423000,
      "action": "Remove",
      "category": "drugs_legal",
      "note": "",
      "enabled": true
    },
    {
      "start_ms": 1428000,
      "end_ms": 1434000,
      "action": "Remove",
      "category": "drugs_legal",
      "note": "",
      "enabled": true
    },
    {
      "start_ms": 1518000,
      "end_ms": 1524000,
      "action": "Remove",
      "category": "drugs_legal",
      "note": "",
      "enabled": true
    },
    {
      "start_ms": 1530000,
      "end_ms": 1531000,
      "action": "Remove",
      "category": "drugs_legal",
      "note": "",
      "enabled": true
    },
    {
      "start_ms": 1902000,
      "end_ms": 1908000,
      "action": "Remove",
      "category": "drugs_legal",
      "note": "",
      "enabled": true
    },
    {
      "start_ms": 2244000,
      "end_ms": 2245000,
      "action": "Remove",
      "category": "drugs_legal",
      "note": "",
      "enabled": true
    },
    {
      "start_ms": 2262000,
      "end_ms": 2263000,
      "action": "Remove",
      "category": "drugs_legal",
      "note": "",
      "enabled": true
    },
    {
      "start_ms": 2772000,
      "end_ms": 2773000,
      "action": "Remove",
      "category": "drugs_legal",
      "note": "",
      "enabled": true
    },
    {
      "start_ms": 3282000,
      "end_ms": 3283000,
      "action": "Remove",
      "category": "racial_slurs",
      "note": "",
      "enabled": true
    },
    {
      "start_ms": 3294000,
      "end_ms": 3295000,
      "action": "Remove",
      "category": "non_graphic",
      "note": "",
      "enabled": true
    },
    {
      "start_ms": 3294000,
      "end_ms": 3295000,
      "action": "Remove",
      "category": "racial_slurs",
      "note": "",
      "enabled": true
    },
    {
      "start_ms": 3300000,
      "end_ms": 3306000,
      "action": "Remove",
      "category": "non_graphic",
      "note": "",
      "enabled": true
    },
    {
      "start_ms": 3384000,
      "end_ms": 3390000,
      "action": "Remove",
      "category": "kissing_normal",
      "note": "",
      "enabled": true
    },
    {
      "start_ms": 3408000,
      "end_ms": 3414000,
      "action": "Remove",
      "category": "drugs_legal",
      "note": "",
      "enabled": true
    },
    {
      "start_ms": 3444000,
      "end_ms": 3456000,
      "action": "Remove",
      "category": "drugs_legal",
      "note": "",
      "enabled": true
    },
    {
      "start_ms": 3516000,
      "end_ms": 3528000,
      "action": "Remove",
      "category": "drugs_legal",
      "note": "",
      "enabled": true
    },
    {
      "start_ms": 3552000,
      "end_ms": 3564000,
      "action": "Remove",
      "category": "drugs_legal",
      "note": "",
      "enabled": true
    },
    {
      "start_ms": 3762000,
      "end_ms": 3763000,
      "action": "Remove",
      "category": "drugs_legal",
      "note": "",
      "enabled": true
    },
    {
      "start_ms": 3840000,
      "end_ms": 3858000,
      "action": "Remove",
      "category": "drugs_legal",
      "note": "",
      "enabled": true
    },
    {
      "start_ms": 3888000,
      "end_ms": 3894000,
      "action": "Remove",
      "category": "drugs_legal",
      "note": "",
      "enabled": true
    },
    {
      "start_ms": 3936000,
      "end_ms": 3942000,
      "action": "Remove",
      "category": "drugs_legal",
      "note": "",
      "enabled": true
    },
    {
      "start_ms": 3972000,
      "end_ms": 3973000,
      "action": "Remove",
      "category": "drugs_legal",
      "note": "",
      "enabled": true
    },
    {
      "start_ms": 4380000,
      "end_ms": 4381000,
      "action": "Remove",
      "category": "disturbing_images",
      "note": "",
      "enabled": true
    },
    {
      "start_ms": 4386000,
      "end_ms": 4387000,
      "action": "Remove",
      "category": "disturbing_images",
      "note": "",
      "enabled": true
    },
    {
      "start_ms": 4392000,
      "end_ms": 4398000,
      "action": "Remove",
      "category": "graphic",
      "note": "",
      "enabled": true
    },
    {
      "start_ms": 4500000,
      "end_ms": 4501000,
      "action": "Remove",
      "category": "drugs_implied",
      "note": "",
      "enabled": true
    },
    {
      "start_ms": 4506000,
      "end_ms": 4507000,
      "action": "Remove",
      "category": "drugs_legal",
      "note": "",
      "enabled": true
    },
    {
      "start_ms": 4524000,
      "end_ms": 4536000,
      "action": "Remove",
      "category": "drugs_legal",
      "note": "",
      "enabled": true
    },
    {
      "start_ms": 4542000,
      "end_ms": 4543000,
      "action": "Remove",
      "category": "drugs_legal",
      "note": "",
      "enabled": true
    },
    {
      "start_ms": 4656000,
      "end_ms": 4662000,
      "action": "Remove",
      "category": "graphic",
      "note": "",
      "enabled": true
    },
    {
      "start_ms": 4704000,
      "end_ms": 4710000,
      "action": "Remove",
      "category": "medical_graphic",
      "note": "",
      "enabled": true
    },
    {
      "start_ms": 4710000,
      "end_ms": 4716000,
      "action": "Remove",
      "category": "medical_graphic",
      "note": "",
      "enabled": true
    },
    {
      "start_ms": 4716000,
      "end_ms": 4722000,
      "action": "Remove",
      "category": "medical_graphic",
      "note": "",
      "enabled": true
    },
    {
      "start_ms": 4752000,
      "end_ms": 4758000,
      "action": "Remove",
      "category": "drugs_legal",
      "note": "",
      "enabled": true
    },
    {
      "start_ms": 4872000,
      "end_ms": 4878000,
      "action": "Remove",
      "category": "drugs_legal",
      "note": "",
      "enabled": true
    },
    {
      "start_ms": 5082000,
      "end_ms": 5083000,
      "action": "Remove",
      "category": "objectionable",
      "note": "",
      "enabled": true
    },
    {
      "start_ms": 5394000,
      "end_ms": 5395000,
      "action": "Remove",
      "category": "drugs_legal",
      "note": "",
      "enabled": true
    },
    {
      "start_ms": 5418000,
      "end_ms": 5419000,
      "action": "Remove",
      "category": "drugs_legal",
      "note": "",
      "enabled": true
    },
    {
      "start_ms": 5424000,
      "end_ms": 5436000,
      "action": "Remove",
      "category": "nudity_without_sex",
      "note": "",
      "enabled": true
    },
    {
      "start_ms": 5460000,
      "end_ms": 5472000,
      "action": "Remove",
      "category": "drugs_legal",
      "note": "",
      "enabled": true
    },
    {
      "start_ms": 6102000,
      "end_ms": 6114000,
      "action": "Remove",
      "category": "objectionable",
      "note": "",
      "enabled": true
    },
    {
      "start_ms": 6204000,
      "end_ms": 6516000,
      "action": "Remove",
      "category": "nudity_without_sex",
      "note": "",
      "enabled": true
    }
  ]
}
