{
  "schema_version": 1,
  "source": "VIDA (Kaggle: benjameeper/movie-violencesexprofanity-data)",
  "imdb_id": "tt4364194",
  "title": "The Peanut Butter Falcon",
  "scenes": [
    {
      "start_ms": 138000,
      "end_ms": 139000,
      "action": "Remove",
      "category": "non_graphic",
      "note": "This data was obtained from https://www.kaggle.com/datasets/benjameeper/movie-violencesexprofanity-data. Timestamps may be incorrect. Please adjust the timing offsets as necessary.",
      "enabled": true
    },
    {
      "start_ms": 228000,
      "end_ms": 229000,
      "action": "Remove",
      "category": "immodesty",
      "note": "",
      "enabled": true
    },
    {
      "start_ms": 228000,
      "end_ms": 229000,
      "action": "Remove",
      "category": "non_graphic",
      "note": "",
      "enabled": true
    },
    {
      "start_ms": 234000,
      "end_ms": 235000,
      "action": "Remove",
      "category": "immodesty",
      "note": "",
      "enabled": true
    },
    {
      "start_ms": 234000,
      "end_ms": 235000,
      "action": "Remove",
      "category": "non_graphic",
      "note": "",
      "enabled": true
    },
    {
      "start_ms": 330000,
      "end_ms": 336000,
      "action": "Remove",
      "category": "immodesty",
      "note": "",
      "enabled": true
    },
    {
      "start_ms": 492000,
      "end_ms": 498000,
      "action": "Remove",
      "category": "immodesty",
      "note": "",
      "enabled": true
    },
    {
      "start_ms": 504000,
      "end_ms": 505000,
      "action": "Remove",
      "category": "racial_slurs",
      "note": "",
      "enabled": true
    },
    {
      "start_ms": 564000,
      "end_ms": 576000,
      "action": "Remove",
      "category": "immodesty",
      "note": "",
      "enabled": true
    },
    {
      "start_ms": 582000,
      "end_ms": 618000,
      "action": "Remove",
      "category": "immodesty",
      "note": "",
      "enabled": true
    },
    {
      "start_ms": 624000,
      "end_ms": 642000,
      "action": "Remove",
      "category": "immodesty",
      "note": "",
      "enabled": true
    },
    {
      "start_ms": 642000,
      "end_ms": 643000,
      "action": "Remove",
      "category": "drugs_legal",
      "note": "",
      "enabled": true
    },
    {
      "start_ms": 642000,
      "end_ms": 654000,
      "action": "Remove",
      "category": "immodesty",
      "note": "",
      "enabled": true
    },
    {
      "start_ms": 690000,
      "end_ms": 696000,
      "action": "Remove",
      "category": "non_graphic",
      "note": "",
      "enabled": true
    },
    {
      "start_ms": 714000,
      "end_ms": 715000,
      "action": "Remove",
      "category": "non_graphic",
      "note": "",
      "enabled": true
    },
    {
      "start_ms": 714000,
      "end_ms": 715000,
      "action": "Remove",
      "category": "objectionable",
      "note": "",
      "enabled": true
    },
    {
      "start_ms": 726000,
      "end_ms": 732000,
      "action": "Remove",
      "category": "immodesty",
      "note": "",
      "enabled": true
    },
    {
      "start_ms": 804000,
      "end_ms": 834000,
      "action": "Remove",
      "category": "drugs_legal",
      "note": "",
      "enabled": true
    },
    {
      "start_ms": 984000,
      "end_ms": 990000,
      "action": "Remove",
      "category": "bodily_functions",
      "note": "",
      "enabled": true
    },
    {
      "start_ms": 990000,
      "end_ms": 991000,
      "action": "Remove",
      "category": "objectionable",
      "note": "",
      "enabled": true
    },
    {
      "start_ms": 1008000,
      "end_ms": 1014000,
      "action": "Remove",
      "category": "objectionable",
      "note": "",
      "enabled": true
    },
    {
      "start_ms": 1038000,
      "end_ms": 1044000,
      "action": "Remove",
      "category": "bodily_functions",
      "note": "",
      "enabled": true
    },
    {
      "start_ms": 1146000,
      "end_ms": 1152000,
      "action": "Remove",
      "category": "immodesty",
      "note": "",
      "enabled": true
    },
    {
      "start_ms": 1164000,
      "end_ms": 1170000,
      "action": "Remove",
      "category": "immodesty",
      "note": "",
      "enabled": true
    },
    {
      "start_ms": 1188000,
      "end_ms": 1236000,
      "action": "Remove",
      "category": "immodesty",
      "note": "",
      "enabled": true
    },
    {
      "start_ms": 1242000,
      "end_ms": 1243000,
      "action": "Remove",
      "category": "immodesty",
      "note": "",
      "enabled": true
    },
    {
      "start_ms": 1248000,
      "end_ms": 1254000,
      "action": "Remove",
      "category": "immodesty",
      "note": "",
      "enabled": true
    },
    {
      "start_ms": 1260000,
      "end_ms": 1266000,
      "action": "Remove",
      "category": "immodesty",
      "note": "",
      "enabled": true
    },
    {
      "start_ms": 1266000,
      "end_ms": 1284000,
      "action": "Remove",
      "category": "immodesty",
      "note": "",
      "enabled": true
    },
    {
      "start_ms": 1314000,
      "end_ms": 1326000,
      "action": "Remove",
      "category": "immodesty",
      "note": "",
      "enabled": true
    },
    {
      "start_ms": 1332000,
      "end_ms": 1338000,
      "action": "Remove",
      "category": "immodesty",
      "note": "",
      "enabled": true
    },
    {
      "start_ms": 1428000,
      "end_ms": 1429000,
      "action": "Remove",
      "category": "racial_slurs",
      "note": "",
      "enabled": true
    },
    {
      "start_ms": 1428000,
      "end_ms": 1434000,
      "action": "Remove",
      "category": "racial_slurs",
      "note": "",
      "enabled": true
    },
    {
      "start_ms": 1452000,
      "end_ms": 1453000,
      "action": "Remove",
      "category": "immodesty",
      "note": "",
      "enabled": true
    },
    {
      "start_ms": 1452000,
      "end_ms": 1453000,
      "action": "Remove",
      "category": "non_graphic",
      "note": "",
      "enabled": true
    },
    {
      "start_ms": 1452000,
      "end_ms": 1453000,
      "action": "Remove",
      "category": "racial_slurs",
      "note": "",
      "enabled": true
    },
    {
      "start_ms": 1452000,
      "end_ms": 1458000,
      "action": "Remove",
      "category": "non_graphic",
      "note": "",
      "enabled": true
    },
    {
      "start_ms": 1464000,
      "end_ms": 1476000,
      "action": "Remove",
      "category": "bodily_functions",
      "note": "",
      "enabled": true
    },
    {
      "start_ms": 1464000,
      "end_ms": 1476000,
      "action": "Remove",
      "category": "immodesty",
      "note": "",
      "enabled": true
    },
    {
      "start_ms": 1488000,
      "end_ms": 1494000,
      "action": "Remove",
      "category": "immodesty",
      "note": "",
      "enabled": true
    },
    {
      "start_ms": 1506000,
      "end_ms": 1512000,
      "action": "Remove",
      "category": "immodesty",
      "note": "",
      "enabled": true
    },
    {
      "start_ms": 1524000,
      "end_ms": 1525000,
      "action": "Remove",
      "category": "immodesty",
      "note": "",
      "enabled": true
    },
    {
      "start_ms": 1542000,
      "end_ms": 1554000,
      "action": "Remove",
      "category": "drugs_legal",
      "note": "",
      "enabled": true
    },
    {
      "start_ms": 1560000,
      "end_ms": 1566000,
      "action": "Remove",
      "category": "drugs_legal",
      "note": "",
      "enabled": true
    },
    {
      "start_ms": 1800000,
      "end_ms": 1806000,
      "action": "Remove",
      "category": "drugs_legal",
      "note": "",
      "enabled": true
    },
    {
      "start_ms": 1806000,
      "end_ms": 1812000,
      "action": "Remove",
      "category": "drugs_legal",
      "note": "",
      "enabled": true
    },
    {
      "start_ms": 1944000,
      "end_ms": 1945000,
      "action": "Remove",
      "category": "vulgar_gestures",
      "note": "",
      "enabled": true
    },
    {
      "start_ms": 2430000,
      "end_ms": 2431000,
      "action": "Remove",
      "category": "racial_slurs",
      "note": "",
      "enabled": true
    },
    {
      "start_ms": 2508000,
      "end_ms": 2509000,
      "action": "Remove",
      "category": "drugs_legal",
      "note": "",
      "enabled": true
    },
    {
      "start_ms": 2526000,
      "end_ms": 2527000,
      "action": "Remove",
      "category": "drugs_legal",
      "note": "",
      "enabled": true
    },
    {
      "start_ms": 2610000,
      "end_ms": 2616000,
      "action": "Remove",
      "category": "drugs_legal",
      "note": "",
      "enabled": true
    },
    {
      "start_ms": 2646000,
      "end_ms": 2647000,
      "action": "Remove",
      "category": "non_graphic",
      "note": "",
      "enabled": true
    },
    {
      "start_ms": 3072000,
      "end_ms": 3078000,
      "action": "Remove",
      "category": "drugs_legal",
      "note": "",
      "enabled": true
    },
    {
      "start_ms": 3084000,
      "end_ms": 3085000,
      "action": "Remove",
      "category": "drugs_legal",
      "note": "",
      "enabled": true
    },
    {
      "start_ms": 3210000,
      "end_ms": 3216000,
      "action": "Remove",
      "category": "immodesty",
      "note": "",
      "enabled": true
    },
    {
      "start_ms": 3228000,
      "end_ms": 3234000,
      "action": "Remove",
      "category": "immodesty",
      "note": "",
      "enabled": true
    },
    {
      "start_ms": 3234000,
      "end_ms": 3235000,
      "action": "Remove",
      "category": "drugs_legal",
      "note": "",
      "enabled": true
    },
    {
      "start_ms": 3234000,
      "end_ms": 3240000,
      "action": "Remove",
      "category": "immodesty",
      "note": "",
      "enabled": true
    },
    {
      "start_ms": 3240000,
      "end_ms": 3241000,
      "action": "Remove",
      "category": "nudity_without_sex",
      "note": "",
      "enabled": true
    },
    {
      "start_ms": 3246000,
      "end_ms": 3247000,
      "action": "Remove",
      "category": "immodesty",
      "note": "",
      "enabled": true
    },
    {
      "start_ms": 3252000,
      "end_ms": 3253000,
      "action": "Remove",
      "category": "immodesty",
      "note": "",
      "enabled": true
    },
    {
      "start_ms": 3258000,
      "end_ms": 3259000,
      "action": "Remove",
      "category": "drugs_legal",
      "note": "",
      "enabled": true
    },
    {
      "start_ms": 3258000,
      "end_ms": 3264000,
      "action": "Remove",
      "category": "immodesty",
      "note": "",
      "enabled": true
    },
    {
      "start_ms": 3288000,
      "end_ms": 3294000,
      "action": "Remove",
      "category": "bodily_functions",
      "note": "",
      "enabled": true
    },
    {
      "start_ms": 3288000,
      "end_ms": 3300000,
      "action": "Remove",
      "category": "immodesty",
      "note": "",
      "enabled": true
    },
    {
      "start_ms": 3390000,
      "end_ms": 3402000,
      "action": "Remove",
      "category": "immodesty",
      "note": "",
      "enabled": true
    },
    {
      "start_ms": 3438000,
      "end_ms": 3444000,
      "action": "Remove",
      "category": "immodesty",
      "note": "",
      "enabled": true
    },
    {
      "start_ms": 3456000,
      "end_ms": 3462000,
      "action": "Remove",
      "category": "immodesty",
      "note": "",
      "enabled": true
    },
    {
      "start_ms": 3468000,
      "end_ms": 3474000,
      "action": "Remove",
      "category": "immodesty",
      "note": "",
      "enabled": true
    },
    {
      "start_ms": 3588000,
      "end_ms": 3589000,
      "action": "Remove",
      "category": "racial_slurs",
      "note": "",
      "enabled": true
    },
    {
      "start_ms": 3594000,
      "end_ms": 3595000,
      "action": "Remove",
      "category": "racial_slurs",
      "note": "",
      "enabled": true
    },
    {
      "start_ms": 3594000,
      "end_ms": 3595000,
      "action": "Remove",
      "category": "racial_slurs",
      "note": "",
      "enabled": true
    },
    {
      "start_ms": 3600000,
      "end_ms": 3601000,
      "action": "Remove",
      "category": "racial_slurs",
      "note": "",
      "enabled": true
    },
    {
      "start_ms": 3642000,
      "end_ms": 3648000,
      "action": "Remove",
      "category": "non_graphic",
      "note": "",
      "enabled": true
    },
    {
      "start_ms": 3798000,
      "end_ms": 3799000,
      "action": "Remove",
      "category": "immodesty",
      "note": "",
      "enabled": true
    },
    {
      "start_ms": 3816000,
      "end_ms": 3822000,
      "action": "Remove",
      "category": "immodesty",
      "note": "",
      "enabled": true
    },
    {
      "start_ms": 3822000,
      "end_ms": 3823000,
      "action": "Remove",
      "category": "immodesty",
      "note": "",
      "enabled": true
    },
    {
      "start_ms": 3894000,
      "end_ms": 3895000,
      "action": "Remove",
      "category": "drugs_legal",
      "note": "",
      "enabled": true
    },
    {
      "start_ms": 4164000,
      "end_ms": 4170000,
      "action": "Remove",
      "category": "sexual_reference",
      "note": "",
      "enabled": true
    },
    {
      "start_ms": 4704000,
      "end_ms": 4710000,
      "action": "Remove",
      "category": "drugs_legal",
      "note": "",
      "enabled": true
    },
    {
      "start_ms": 4722000,
      "end_ms": 4728000,
      "action": "Remove",
      "category": "drugs_legal",
      "note": "",
      "enabled": true
    },
    {
      "start_ms": 4734000,
      "end_ms": 4735000,
      "action": "Remove",
      "category": "drugs_legal",
      "note": "",
      "enabled": true
    },
    {
      "start_ms": 4752000,
      "end_ms": 4758000,
      "action": "Remove",
      "category": "drugs_legal",
      "note": "",
      "enabled": true
    },
    {
      "start_ms": 4758000,
      "end_ms": 4764000,
      "action": "Remove",
      "category": "drugs_legal",
      "note": "",
      "enabled": true
    },
    {
      "start_ms": 4806000,
      "end_ms": 4812000,
      "action": "Remove",
      "category": "graphic",
      "note": "",
      "enabled": true
    },
    {
      "start_ms": 4812000,
      "end_ms": 4813000,
      "action": "Remove",
      "category": "graphic",
      "note": "",
      "enabled": true
    },
    {
      "start_ms": 4818000,
      "end_ms": 4819000,
      "action": "Remove",
      "category": "non_graphic",
      "note": "",
      "enabled": true
    },
    {
      "start_ms": 4830000,
      "end_ms": 4831000,
      "action": "Remove",
      "category": "graphic",
      "note": "",
      "enabled": true
    },
    {
      "start_ms": 4836000,
      "end_ms": 4842000,
      "action": "Remove",
      "category": "non_graphic",
      "note": "",
      "enabled": true
    },
    {
      "start_ms": 4848000,
      "end_ms": 4849000,
      "action": "Remove",
      "category": "non_graphic",
      "note": "",
      "enabled": true
    },
    {
      "start_ms": 4866000,
      "end_ms": 4872000,
      "action": "Remove",
      "category": "graphic",
      "note": "",
      "enabled": true
    },
    {
      "start_ms": 5028000,
      "end_ms": 5040000,
      "action": "Remove",
      "category": "kissing_normal",
      "note": "",
      "enabled": true
    },
    {
      "start_ms": 5070000,
      "end_ms": 5071000,
      "action": "Remove",
      "category": "drugs_implied",
      "note": "",
      "enabled": true
    },
    {
      "start_ms": 5106000,
      "end_ms": 5107000,
      "action": "Remove",
      "category": "drugs_legal",
      "note": "",
      "enabled": true
    },
    {
      "start_ms": 5118000,
      "end_ms": 5124000,
      "action": "Remove",
      "category": "drugs_legal",
      "note": "",
      "enabled": true
    },
    {
      "start_ms": 5130000,
      "end_ms": 5136000,
      "action": "Remove",
      "category": "drugs_legal",
      "note": "",
      "enabled": true
    },
    {
      "start_ms": 5184000,
      "end_ms": 5190000,
      "action": "Remove",
      "category": "non_graphic",
      "note": "",
      "enabled": true
    },
    {
      "start_ms": 5202000,
      "end_ms": 5208000,
      "action": "Remove",
      "category": "non_graphic",
      "note": "",
      "enabled": true
    },
    {
      "start_ms": 5220000,
      "end_ms": 5221000,
      "action": "Remove",
      "category": "non_graphic",
      "note": "",
      "enabled": true
    },
    {
      "start_ms": 5220000,
      "end_ms": 5221000,
      "action": "Remove",
      "category": "racial_slurs",
      "note": "",
      "enabled": true
    },
    {
      "start_ms": 5262000,
      "end_ms": 5263000,
      "action": "Remove",
      "category": "vulgar_gestures",
      "note": "",
      "enabled": true
    },
    {
      "start_ms": 5316000,
      "end_ms": 5317000,
      "action": "Remove",
      "category": "non_graphic",
      "note": "",
      "enabled": true
    },
    {
      "start_ms": 5328000,
      "end_ms": 5329000,
      "action": "Remove",
      "category": "non_graphic",
      "note": "",
      "enabled": true
    }
  ]
}
